adaptor/adapter.py
adaptor/mcp2221.py
asfv1/.git
asfv1/.gitignore
asfv1/LICENSE
asfv1/README.md
asfv1/asfv1.py
asfv1/example.asm
asfv1/setup.py
disfv1/.git
disfv1/.gitignore
disfv1/LICENSE
disfv1/README.md
disfv1/disfv1.py
disfv1/example.bin
disfv1/setup.py
eeprom/eeprom.py
fv1_programmer/dialogs.css
fv1_programmer/dialogs.py
fv1_programmer/fv1.py
fv1_programmer/main.py
fv1_programmer/pyinstaller.py
fv1_programmer/tui.css
fv1_programmer/tui.py
fv1_programmer-0.5.2.dist-info/LICENSE
fv1_programmer-0.5.2.dist-info/METADATA
fv1_programmer-0.5.2.dist-info/WHEEL
fv1_programmer-0.5.2.dist-info/entry_points.txt
fv1_programmer-0.5.2.dist-info/RECORD
