Metadata-Version: 2.1
Name: fv1-programmer
Version: 0.5.2
Summary: An FV-1 assembler/disassembler and EEPROM programming tool for the Spin Semiconductor FV-1 DSP
Home-page: https://github.com/audiofab/fv1_programmer
License: MIT
Author: Mark Melvin
Author-email: mark.melvin@audiofab.com
Requires-Python: >=3.8,<3.13
Classifier: Development Status :: 4 - Beta
Classifier: Environment :: Console
Classifier: Intended Audience :: Developers
Classifier: License :: OSI Approved :: MIT License
Classifier: Operating System :: Microsoft :: Windows :: Windows 10
Classifier: Operating System :: Microsoft :: Windows :: Windows 11
Classifier: Programming Language :: Python :: 3
Classifier: Programming Language :: Python :: 3.8
Classifier: Programming Language :: Python :: 3.9
Classifier: Programming Language :: Python :: 3.10
Classifier: Programming Language :: Python :: 3.11
Classifier: Programming Language :: Python :: 3.10
Classifier: Programming Language :: Python :: 3.11
Classifier: Programming Language :: Python :: 3.7
Classifier: Programming Language :: Python :: 3.8
Classifier: Programming Language :: Python :: 3.9
Classifier: Typing :: Typed
Requires-Dist: easymcp2221 (>=1.6.2,<2.0.0)
Requires-Dist: intelhex (>=2.3.0,<3.0.0)
Requires-Dist: pyperclip (>=1.8.2,<2.0.0)
Requires-Dist: textual (>=0.55.0,<0.56.0)
